README.md
setup.py
lxtoolkit/__init__.py
lxtoolkit.egg-info/PKG-INFO
lxtoolkit.egg-info/SOURCES.txt
lxtoolkit.egg-info/dependency_links.txt
lxtoolkit.egg-info/top_level.txt
lxtoolkit/cv/__init__.py
lxtoolkit/cv/datasets/BiDatasetFolder.py
lxtoolkit/cv/datasets/__init__.py
lxtoolkit/cv/evaluation/Miscellaneous.py
lxtoolkit/cv/evaluation/__init__.py
lxtoolkit/cv/evaluation/cal_acc.py
lxtoolkit/cv/evaluation/img_cla_eval.py
lxtoolkit/cv/models/AlexNet.py
lxtoolkit/cv/models/LeNet.py
lxtoolkit/cv/models/MLP.py
lxtoolkit/cv/models/__init__.py
lxtoolkit/cv/train/__init__.py
lxtoolkit/cv/train/img_cla_train.py